eflowcalc/__init__.py
eflowcalc/eflowcalc.py
eflowcalc/flow_duration.py
eflowcalc/flow_frequency.py
eflowcalc/flow_magnitude.py
eflowcalc/flow_rate_change.py
eflowcalc/flow_timing.py
eflowcalc/tools.py
eflowcalc/version.py
eflowcalc-0.1.0.dist-info/LICENCE.rst
eflowcalc-0.1.0.dist-info/METADATA
eflowcalc-0.1.0.dist-info/WHEEL
eflowcalc-0.1.0.dist-info/top_level.txt
eflowcalc-0.1.0.dist-info/RECORD
