Metadata-Version: 2.1
Name: eflowcalc
Version: 0.1.0
Summary: EFlowCalc: A Calculator of Streamflow Characteristics in Python
Home-page: UNKNOWN
Author: Thibault Hallouin
Author-email: thibault.hallouin@ucdconnect.ie
License: GPLv3
Download-URL: https://pypi.python.org/pypi/eflowcalc
Project-URL: Bug Tracker, https://github.com/thibhlln/eflowcalc/issues
Project-URL: Source Code, https://github.com/thibhlln/eflowcalc
Project-URL: Documentation, https://thibhlln.github.io/eflowcalc
Platform: UNKNOWN
Classifier: Development Status :: 4 - Beta
Classifier: Natural Language :: English
Classifier: Intended Audience :: Science/Research
Classifier: Intended Audience :: Developers
Classifier: Topic :: Scientific/Engineering :: Hydrology
Classifier: Operating System :: MacOS
Classifier: Operating System :: Microsoft :: Windows
Classifier: Operating System :: POSIX :: Linux
Classifier: License :: OSI Approved :: GNU General Public License v3 (GPLv3)
Classifier: Programming Language :: Python :: 3.7
Classifier: Programming Language :: Python :: 3.8
Classifier: Programming Language :: Python :: 3.9
Classifier: Programming Language :: Python :: Implementation :: CPython
Requires-Dist: numpy
Requires-Dist: pandas
Provides-Extra: tests
Requires-Dist: netCDF4 ; extra == 'tests'
Requires-Dist: cftime ; extra == 'tests'
